odoo/addons/l10n_us_gaap/README.rst
odoo/addons/l10n_us_gaap/__init__.py
odoo/addons/l10n_us_gaap/__manifest__.py
odoo/addons/l10n_us_gaap/data/account_chart_template_data_load.xml
odoo/addons/l10n_us_gaap/data/res_company_data.xml
odoo/addons/l10n_us_gaap/data/template/account.account-us_gaap.csv
odoo/addons/l10n_us_gaap/data/template/account.tax.group-us_gaap.csv
odoo/addons/l10n_us_gaap/docs/l10n_us_gaap_trial_balance.ods
odoo/addons/l10n_us_gaap/i18n/es.po
odoo/addons/l10n_us_gaap/i18n/l10n_us_gaap.pot
odoo/addons/l10n_us_gaap/models/__init__.py
odoo/addons/l10n_us_gaap/models/template_us_gaap.py
odoo/addons/l10n_us_gaap/readme/CONTRIBUTORS.md
odoo/addons/l10n_us_gaap/readme/DESCRIPTION.md
odoo/addons/l10n_us_gaap/readme/INSTALL.md
odoo/addons/l10n_us_gaap/readme/USAGE.md
odoo/addons/l10n_us_gaap/static/description/icon.png
odoo/addons/l10n_us_gaap/static/description/index.html
odoo/addons/l10n_us_gaap/tests/__init__.py
odoo/addons/l10n_us_gaap/tests/test_base_us.py
odoo_addon_l10n_us_gaap-17.0.1.0.0.6.dist-info/METADATA
odoo_addon_l10n_us_gaap-17.0.1.0.0.6.dist-info/WHEEL
odoo_addon_l10n_us_gaap-17.0.1.0.0.6.dist-info/top_level.txt
odoo_addon_l10n_us_gaap-17.0.1.0.0.6.dist-info/RECORD
